isyntax/__init__.py
isyntax/_pyisyntax.pyd
isyntax/wrapper.py
isyntax/lowlevel/__init__.py
isyntax/lowlevel/io_management.py
isyntax/lowlevel/libisyntax.py
pyisyntax-0.1.5.dist-info/licenses/LICENSE
pyisyntax-0.1.5.dist-info/METADATA
pyisyntax-0.1.5.dist-info/WHEEL
pyisyntax-0.1.5.dist-info/top_level.txt
pyisyntax-0.1.5.dist-info/RECORD
