Metadata-Version: 2.4
Name: pyisyntax
Version: 0.1.5
Summary: Python bindings for libisyntax
Author-email: Aiden Nibali <dismaldenizen@gmail.com>
License-Expression: MIT
Project-URL: Homepage, https://github.com/anibali/pyisyntax
Project-URL: Source, https://github.com/anibali/pyisyntax
Project-URL: Download, https://pypi.org/project/pyisyntax/#files
Project-URL: Tracker, https://github.com/anibali/pyisyntax/issues
Project-URL: Release notes, https://github.com/anibali/pyisyntax/blob/master/CHANGELOG.md
Requires-Python: >=3.10
License-File: LICENSE
Requires-Dist: cffi>=1.12
Requires-Dist: numpy
Dynamic: license-file
